miaApplicazione/__init__.py
miaApplicazione/admin.py
miaApplicazione/apps.py
miaApplicazione/models.py
miaApplicazione/urls.py
miaApplicazione/views.py
miaApplicazione/migrations/0001_initial.py
miaApplicazione/migrations/0002_alter_utenza_datanascita.py
miaApplicazione/migrations/__init__.py
mioProgetto/__init__.py
mioProgetto/asgi.py
mioProgetto/settings.py
mioProgetto/urls.py
mioProgetto/wsgi.py
mioProgetto-1.0.dist-info/METADATA
mioProgetto-1.0.dist-info/WHEEL
mioProgetto-1.0.dist-info/top_level.txt
mioProgetto-1.0.dist-info/RECORD
