Metadata-Version: 2.1
Name: mioProgetto
Version: 1.0
Summary: mioProgetto
Home-page: https://gitlab.com/magni5/2022_assignment1_itis.git
Author: Gruppo ITIS
Requires-Python: >=3
